Ameme/Trainer.py
Ameme/TrainerConfig.py
Ameme/__init__.py
Ameme/losses/LabelSmoothing.py
Ameme/losses/__init__.py
Ameme/metrics/AverageMeter.py
Ameme/metrics/RocAucMeter.py
Ameme/metrics/__init__.py
Ameme-0.0.6.dist-info/LICENSE
Ameme-0.0.6.dist-info/METADATA
Ameme-0.0.6.dist-info/WHEEL
Ameme-0.0.6.dist-info/top_level.txt
Ameme-0.0.6.dist-info/RECORD
