Metadata-Version: 2.1
Name: Ameme
Version: 0.0.6
Summary: my tools
Home-page: https://github.com/yyh0806/Ameme
Author: yangyuhui
Author-email: yangyuhui@jaist.ac.jp
License: UNKNOWN
Platform: UNKNOWN
Classifier: Programming Language :: Python :: 3
Classifier: License :: OSI Approved :: MIT License
Classifier: Operating System :: OS Independent
